{
  "$schema": "http://json-schema.org/draft-07/schema#",
  "$id": "https://fdc3.finos.org/schemas/2.2/context/timeRange.schema.json",
  "type": "object",
  "title": "TimeRange",
  "description": "A context representing a period of time. Any user interfaces that represent or visualize events or activity over time can be filtered or focused on a particular time period, e.g.:\n\n- A pricing chart\n- A trade blotter\n- A record of client contact/activity in a CRM\n\nExample use cases:\n\n- User may want to view pricing/trades/customer activity for a security over a particular time period, the time range might be specified as the context for the `ViewChart` intent OR it might be embedded in another context (e.g. a context representing a chart to plot).\n- User filters a visualization (e.g. a pricing chart) to show a particular period, the `TimeRange` is broadcast and other visualizations (e.g. a heatmap of activity by instrument, or industry sector etc.) receive it and filter themselves to show data over the same range.\n\nNotes:\n\n- A `TimeRange` may be closed (i.e. `startTime` and `endTime` are both known) or open (i.e. only one of `startTime` or `endTime` is known).\n- Ranges corresponding to dates (e.g. `2022-05-12` to `2022-05-19`) should be specified using times as this prevents issues with timezone conversions and inclusive/exclusive date ranges.\n- String fields representing times are encoded according to [ISO 8601-1:2019](https://www.iso.org/standard/70907.html).\n  - A timezone indicator should be specified, e.g. `\"2022-05-12T15:18:03Z\"` or `\"2022-05-12T16:18:03+01:00\"`\n  - Times MAY be specified with millisecond precision, e.g. `\"2022-05-12T15:18:03.349Z\"`",
  "allOf": [
    {
      "properties": {
        "type": {
          "const": "fdc3.timeRange"
        },
        "startTime": {
          "type": "string",
          "format": "date-time",
          "title": "Start Time",
          "description": "The start time of the range, encoded according to [ISO 8601-1:2019](https://www.iso.org/standard/70907.html) with a timezone indicator."
        },
        "endTime": {
          "type": "string",
          "format": "date-time",
          "title": "End Time",
          "description": "The end time of the range, encoded according to [ISO 8601-1:2019](https://www.iso.org/standard/70907.html) with a timezone indicator."
        }
      }
    },
    { "$ref": "context.schema.json#/definitions/BaseContext" }
  ],
  "oneOf": [
    {
      "required": [
        "startTime",
        "endTime"
      ]
    },
    {
      "required": [
        "startTime"
      ]
    },
    {
      "required": [
        "endTime"
      ]
    }
  ],
  "examples": [
    {
      "type": "fdc3.timeRange",
      "startTime": "2022-03-30T15:44:44Z",
      "endTime": "2022-04-30T23:59:59ZS"
    },
    {
      "type": "fdc3.timeRange",
      "startTime": "2022-03-30T15:44:44+00:00"
    },
    {
      "type": "fdc3.timeRange",
      "endTime": "2022-03-30T16:44:44.123Z"
    }
  ]
}