{
  "unversionedId": "trademarks",
  "id": "version-2.0/trademarks",
  "title": "Trademarks",
  "description": "The trademarks, logos, and service marks not owned on behalf of FDC3 and FINOS and that are displayed on the Site are the registered and unregistered marks of their respective owners. No rights are granted by the FDC3 or FINOS to use such marks, whether by implication, estoppel, or otherwise.",
  "source": "@site/versioned_docs/version-2.0/trademarks.md",
  "sourceDirName": ".",
  "slug": "/trademarks",
  "permalink": "/docs/trademarks",
  "draft": false,
  "tags": [],
  "version": "2.0",
  "lastUpdatedBy": "Author",
  "lastUpdatedAt": 1539502055,
  "formattedLastUpdatedAt": "Oct 14, 2018",
  "frontMatter": {
    "title": "Trademarks",
    "original_id": "trademarks"
  }
}