{
  "unversionedId": "intents-intro",
  "id": "version-1.0/intents-intro",
  "title": "Intents Overview",
  "description": "Extending APIs from one application to another is powerful. However, it requires bi-lateral agreements where implementors build to proprietary APIs. A standard language for interaction between applications allows us to create workflows on the fly, so that applications can discover and link to another without any prior knowledge.",
  "source": "@site/versioned_docs/version-1.0/intents-intro.md",
  "sourceDirName": ".",
  "slug": "/intents-intro",
  "permalink": "/docs/1.0/intents-intro",
  "draft": false,
  "tags": [],
  "version": "1.0",
  "lastUpdatedBy": "Author",
  "lastUpdatedAt": 1539502055,
  "formattedLastUpdatedAt": "Oct 14, 2018",
  "frontMatter": {
    "sidebar_label": "Intents Overview",
    "title": "Intents Overview",
    "hide_title": true,
    "original_id": "intents-intro"
  },
  "sidebar": "version-1.0/docs",
  "previous": {
    "title": "Errors",
    "permalink": "/docs/1.0/api/Errors"
  },
  "next": {
    "title": "Intents Specification",
    "permalink": "/docs/1.0/intents-spec"
  }
}